build/lib/redtongue/__init__.py
build/lib/redtongue/redtongue.py
redtongue/__init__.py
redtongue/redtongue.py
redtongue-0.0.1.dist-info/LICENSE
redtongue-0.0.1.dist-info/METADATA
redtongue-0.0.1.dist-info/WHEEL
redtongue-0.0.1.dist-info/top_level.txt
redtongue-0.0.1.dist-info/RECORD
