Metadata-Version: 2.1
Name: redtongue
Version: 0.0.1
Summary: niu bi redtongue!!!!
Home-page: https://github.com/redtongue
Author: redtongue
License: UNKNOWN
Platform: UNKNOWN
Classifier: Programming Language :: Python :: 3
Classifier: License :: OSI Approved :: MIT License
Classifier: Operating System :: OS Independent
